rest_auth/__init__.py
rest_auth/apps.py
rest_auth/default_settings.py
rest_auth/serializers.py
rest_auth/urls.py
rest_auth/views.py
rest_auth/contrib/__init__.py
rest_auth/contrib/rest_framework/__init__.py
rest_auth/contrib/rest_framework/decorators.py
rest_auth/migrations/__init__.py
rest_auth/users/__init__.py
rest_auth/users/apps.py
rest_auth/users/routers.py
rest_auth/users/serializers.py
rest_auth/users/urls.py
rest_auth/users/views.py
rest_auth/users/migrations/__init__.py
django_rest_framework_auth-0.9.0.dist-info/LICENSE
django_rest_framework_auth-0.9.0.dist-info/METADATA
django_rest_framework_auth-0.9.0.dist-info/WHEEL
django_rest_framework_auth-0.9.0.dist-info/top_level.txt
django_rest_framework_auth-0.9.0.dist-info/RECORD
