Metadata-Version: 2.1
Name: django-rest-framework-auth
Version: 0.9.0
Summary: django authentication meets rest framework
Home-page: http://github.com/lordpeara/django-rest-auth
Author: lordpeara
Author-email: lordpeara@gmail.com
License: MIT
Keywords: django rest auth rest-framework authentication api
Platform: UNKNOWN
Requires-Dist: djangorestframework (>=3.7)
Requires-Dist: Django (<2.0,>=1.11.21) ; python_version < "3.0"
Requires-Dist: Django (<2.2,>=2.0) ; python_version >= "3.0"
